django_hornet/__init__.py
django_hornet/admin.py
django_hornet/apps.py
django_hornet/manager.py
django_hornet/middleware.py
django_hornet/models.py
django_hornet/tests.py
django_hornet/views.py
django_hornet/migrations/__init__.py
django_hornet/templatetags/__init__.py
django_hornet/templatetags/hornet_helpers.py
django_hornet-0.1.6.dist-info/licenses/LICENSE
django_hornet-0.1.6.dist-info/METADATA
django_hornet-0.1.6.dist-info/WHEEL
django_hornet-0.1.6.dist-info/top_level.txt
django_hornet-0.1.6.dist-info/RECORD
